mirage/__init__.py
mirage/mirage.py
miragepy-0.0.2.dist-info/LICENSE
miragepy-0.0.2.dist-info/METADATA
miragepy-0.0.2.dist-info/WHEEL
miragepy-0.0.2.dist-info/entry_points.txt
miragepy-0.0.2.dist-info/top_level.txt
miragepy-0.0.2.dist-info/RECORD
