Metadata-Version: 2.1
Name: miragepy
Version: 0.0.2
Summary: 🏖 mirage is a static site generator in Python
Author-email: Kaan Giray Buzluk <kaangiray26@protonmail.com>
License: MIT License
Project-URL: Homepage, https://github.com/kaangiray26/mirage
Project-URL: Bug Tracker, https://github.com/kaangiray26/mirage/issues
Classifier: Programming Language :: Python :: 3
Classifier: License :: OSI Approved :: GNU General Public License v3 (GPLv3)
Classifier: Operating System :: OS Independent
Requires-Python: >=3.8
License-File: LICENSE
Requires-Dist: quart
Requires-Dist: markdown
Requires-Dist: pyyaml
